presql/__init__.py
presql/presql.py
presql-1.0.2.dist-info/LICENSE
presql-1.0.2.dist-info/METADATA
presql-1.0.2.dist-info/WHEEL
presql-1.0.2.dist-info/top_level.txt
presql-1.0.2.dist-info/RECORD
