Metadata-Version: 2.1
Name: presql
Version: 1.0.2
Summary: PostgreSQL and Psycopg2 wrapper.
Home-page: https://github.com/rmaniego/presql
Author: Rodney Maniego Jr.
Author-email: rod.maniego23@gmail.com
License: MIT
Download-URL: https://github.com/rmaniego/presql/archive/v1.0.tar.gz
Keywords: postgresql,postgres,psycopg2,sql,python
Platform: UNKNOWN
Classifier: Development Status :: 5 - Production/Stable
Classifier: Intended Audience :: Developers
Classifier: Topic :: Software Development :: Build Tools
Classifier: License :: OSI Approved :: MIT License
Classifier: Programming Language :: Python :: 3
Requires-Python: >=3.6
License-File: LICENSE
Requires-Dist: psycopg2
Requires-Dist: psycopg2-binary
